bowtie/__init__.py
bowtie/_app.py
bowtie/_cache.py
bowtie/_command.py
bowtie/_component.py
bowtie/_magic.py
bowtie/_progress.py
bowtie/_typing.py
bowtie/_utils.py
bowtie/auth.py
bowtie/control.py
bowtie/exceptions.py
bowtie/html.py
bowtie/pager.py
bowtie/visual.py
bowtie/feedback/__init__.py
bowtie/feedback/message.py
bowtie/src/button.jsx
bowtie/src/datagrid.jsx
bowtie/src/date.jsx
bowtie/src/div.jsx
bowtie/src/dropdown.jsx
bowtie/src/griddle.jsx
bowtie/src/header.jsx
bowtie/src/link.jsx
bowtie/src/markdown.jsx
bowtie/src/nouislider.jsx
bowtie/src/number.jsx
bowtie/src/package.json
bowtie/src/plotly.jsx
bowtie/src/progress.jsx
bowtie/src/slider.jsx
bowtie/src/svg.jsx
bowtie/src/switch.jsx
bowtie/src/table.jsx
bowtie/src/textbox.jsx
bowtie/src/upload.jsx
bowtie/src/utils.js
bowtie/src/view.jsx
bowtie/src/webpack.dev.js
bowtie/src/webpack.prod.js
bowtie/templates/bowtie.html
bowtie/templates/components.js.j2
bowtie/templates/index.jsx.j2
bowtie/templates/webpack.common.js.j2
bowtie/tests/__init__.py
bowtie/tests/conftest.py
bowtie/tests/test_app.py
bowtie/tests/test_cache.py
bowtie/tests/test_command.py
bowtie/tests/test_compile.py
bowtie/tests/test_components.py
bowtie/tests/test_editor.py
bowtie/tests/test_layout.py
bowtie/tests/test_multiple.py
bowtie/tests/test_plotly.py
bowtie/tests/test_serialize.py
bowtie/tests/test_tags.py
bowtie/tests/test_utils.py
bowtie/tests/utils.py
bowtie-0.11.0.dist-info/LICENSE
bowtie-0.11.0.dist-info/WHEEL
bowtie-0.11.0.dist-info/METADATA
bowtie-0.11.0.dist-info/RECORD
