Metadata-Version: 2.1
Name: bowtie
Version: 0.11.0
Summary: Interactive Dashboard Toolkit.
Home-page: https://github.com/jwkvam/bowtie
License: UNKNOWN
Keywords: dashboard visualization interactive visualize
Author: Jacques Kvam
Author-email: jwkvam+pypi@gmail.com
Requires-Python: >=3.6
Classifier: License :: OSI Approved :: MIT License
Classifier: Programming Language :: Python :: 3
Classifier: Programming Language :: Python :: 3.6
Classifier: Programming Language :: Python :: 3.7
Requires-Dist: click
Requires-Dist: eventlet
Requires-Dist: flask
Requires-Dist: flask-socketio
Requires-Dist: jinja2
Requires-Dist: markdown
Requires-Dist: msgpack
Provides-Extra: .none
